apcloudy/__init__.py
apcloudy/client.py
apcloudy/config.py
apcloudy/exceptions.py
apcloudy/jobs_manager.py
apcloudy/models.py
apcloudy/project_manager.py
apcloudy/spiders_manager.py
apcloudy/utils.py
apcloudy-0.1.6.dist-info/licenses/LICENSE
apcloudy-0.1.6.dist-info/METADATA
apcloudy-0.1.6.dist-info/WHEEL
apcloudy-0.1.6.dist-info/top_level.txt
apcloudy-0.1.6.dist-info/RECORD
