Metadata-Version: 2.4
Name: apcloudy
Version: 0.1.6
Summary: A Python client for interacting with the APCloudy platform
Home-page: https://github.com/fawadss1/apcloudy
Author: Fawad Ali
Author-email: Fawad Ali <fawadstar6@gmail.com>
Maintainer-email: Fawad Ali <fawadstar6@gmail.com>
License: MIT
Project-URL: Homepage, https://github.com/fawadss1/apcloudy
Project-URL: Bug Reports, https://github.com/fawadss1/apcloudy/issues
Project-URL: Source, https://github.com/fawadss1/apcloudy
Project-URL: Documentation, https://github.com/fawadss1/apcloudy#readme
Keywords: apcloudy,api,client,web scraping,spiders
Classifier: Development Status :: 3 - Alpha
Classifier: Intended Audience :: Developers
Classifier: License :: OSI Approved :: MIT License
Classifier: Operating System :: OS Independent
Classifier: Programming Language :: Python :: 3
Classifier: Programming Language :: Python :: 3.7
Classifier: Programming Language :: Python :: 3.8
Classifier: Programming Language :: Python :: 3.9
Classifier: Programming Language :: Python :: 3.10
Classifier: Programming Language :: Python :: 3.11
Classifier: Programming Language :: Python :: 3.12
Classifier: Topic :: Internet :: WWW/HTTP
Classifier: Topic :: Software Development :: Libraries :: Python Modules
Requires-Python: >=3.7
License-File: LICENSE
Requires-Dist: requests>=2.32.4
Requires-Dist: tabulate>=0.9.0
Provides-Extra: dev
Requires-Dist: pytest>=6.0; extra == "dev"
Requires-Dist: pytest-cov>=2.0; extra == "dev"
Requires-Dist: black>=21.0; extra == "dev"
Requires-Dist: flake8>=3.8; extra == "dev"
Requires-Dist: mypy>=0.800; extra == "dev"
Dynamic: author
Dynamic: home-page
Dynamic: license-file
Dynamic: requires-python
